Workbook

Sheet Labeled sample
A1: app_name | B1: score | C1: content | D1: category | E1: notes | F1: mentions_mint
A2: Credit Karma | B2: 1 | C2: Horrible 😔 | D2: Other / off-topic | E2: vague negative, no specific issue | F2: no
A3: Credit Karma | B3: 1 | C3: Switching from Mint, I absolutely hate it. The whole app is a collection of ads. No longer useful. | D3: Privacy & trust | E3: about ads | F3: yes
A4: Credit Karma | B4: 1 | C4: Unable to log in no support absolutely. Complete Trash. update: This system completely total garbage will recommend CREDIT SESAME....... | D4: Customer support | E4: login problem; no category fits well | F4: no
A5: Credit Karma | B5: 1 | C5: this app is so predatory | D5: Privacy & trust | E5: vague; could also be Other | F5: no
A6: Credit Karma | B6: 1 | C6: This app keeps popping up automatically on my phone when I don't even have it installed on my phone. How can I stop this from happening? It's so annoying. | D6: Bugs & performance | E6: app appears without being installed | F6: no
A7: Credit Karma | B7: 1 | C7: Once Intuit acquires any product, it becomes the shitiest piece of software. I had an awesome experience with Mint until they decided to move to the Credit Karma Ads portal. Seriously, the most hated company 😒 | D7: Privacy & trust | E7: about ads; anger at Mint move | F7: yes
A8: Credit Karma | B8: 1 | C8: I like the app it's very helpful but it started to stop updating my credit score saying trouble connecting now I don't know what my actual score is | D8: Bugs & performance | E8: credit score not refreshing; not a bank sync issue | F8: no
A9: Credit Karma | B9: 1 | C9: The Credit Karma app wouldn't allow me to sign in with my fingerprint due to too many false positives, and it wouldn't let me log in using my password or PIN code. | D9: Bugs & performance | E9: login problem | F9: no
A10: Credit Karma | B10: 2 | C10: qĺpm | D10: Other / off-topic | E10: gibberish | F10: no
A11: Credit Karma | B11: 2 | C11: Great app | D11: Praise | E11: text and rating don't match | F11: no
A12: Credit Karma | B12: 2 | C12: closed my account for no reason | D12: Customer support | E12: account closed; account issue | F12: no
A13: Credit Karma | B13: 2 | C13: Compared to the Mint application that it supposedly replaced in the intuit suite, It is nearly useless except for the credit score feature and the countless ads. If you are a mint user and are being prompted to switch to credit karma, delay as long as possible. | D13: Privacy & trust | E13: about ads; also missing budgeting features | F13: yes
... A25: Credit Karma | B25: 3 | C25: 👍👍😄🌭 | D25: Praise | E25: emoji only | F25: no
A26: Credit Karma | B26: 4 | C26: Good app | D26: Praise | F26: no
A27: Credit Karma | B27: 4 | C27: Please bring back the old neon color. (Also stop asking me about my driving score. I don't own a car.) | D27: Usability & design | E27: also unwanted prompts (driving score) | F27: no
A28: Credit Karma | B28: 4 | C28: All is good except the GPS is not accurate many times. | D28: Bugs & performance | E28: GPS accuracy; unclear which feature | F28: no
A29: Credit Karma | B29: 4 | C29: good but getting more ad oriented | D29: Privacy & trust | E29: about ads | F29: no
A30: Credit Karma | B30: 4 | C30: great tool, for beginners as well as those more experienced with credit. it really helps that I'm notified when the creditors will be reporting to the credit agency | D30: Praise | F30: no
A31: Credit Karma | B31: 4 | C31: I have time in for better lighting on the phone I would have meet in web there nice. | D31: Other / off-topic | E31: unclear text | F31: no
A32: Credit Karma | B32: 4 | C32: I don't need everyone to know everything with all the scammers out there. | D32: Privacy & trust | E32: vague privacy concern | F32: no
A33: Credit Karma | B33: 4 | C33: Credit karma is one of the best. Apps to use and check your credit. | D33: Praise | F33: no
A34: Credit Karma | B34: 5 | C34: great | D34: Praise | F34: no
A35: Credit Karma | B35: 5 | C35: I Love This App | D35: Praise | F35: no
A36: Credit Karma | B36: 5 | C36: I enjoy keeping up with my credit score and it's fast and easy with Credit Karma. You also get much more info about your credit making it easier to spot issues. | D36: Praise | F36: no
A37: Credit Karma | B37: 5 | C37: This is a very easy app to use. | D37: Praise | F37: no
A38: Credit Karma | B38: 5 | C38: I've been using Ck for years now I love this app. It's helped so much. | D38: Praise | F38: no
A39: Credit Karma | B39: 5 | C39: Credit Karma is a must for those who want to take control of or manage their credit. This is one of the most necessary and useful apps for helping you reach your financial goals. Plus, it's free. | D39: Praise | F39: no
A40: Credit Karma | B40: 5 | C40: I didn't think my credit score would be as good as a 668. 10 to 15 years ago I had a few credit cards and got behind on my payments but finally got them paid off. Now I do not have any credit cards only a debit card and deposit account for my monthly retirement payment. I hope to improve my credit rating a bit. Thank you for your free credit rating service! | D40: Praise | F40: no
A41: Credit Karma | B41: 5 | C41: Great app to stay updated on your credit scores. Also, gives information & options to dispute accounts... well done CK | D41: Praise | F41: no
A42: Monarch Money | B42: 1 | C42: Can't even use my membership App requires new trial after signing into current | D42: Pricing & subscription | E42: paid membership not recognized; could be a bug | F42: no
A43: Monarch Money | B43: 1 | C43: only have yearly pay as an option | D43: Pricing & subscription | E43: no monthly option | F43: no
A44: Monarch Money | B44: 1 | C44: Pay to play kind of apps, fit for US and Canadians only. | D44: Pricing & subscription | E44: also region availability | F44: no
A45: Monarch Money | B45: 1 | C45: I downloaded it for a free trial today and it signed me up via the play store to be billed in 7 days, then I went back into the app and it says I have to pay now because I've used my trial. I never have used it and I guess now I never can. | D45: Pricing & subscription | E45: trial billing problem | F45: no
A46: Monarch Money | B46: 1 | C46: Requires monthly subscription. No thanks, I can track my own finances. Ironic that an app to help with your finances requires you pay a monthly bill. Edit to say them still trying to sell me on this bs is so sad XD | D46: Pricing & subscription | E46: also upselling | F46: no
A47: Monarch Money | B47: 1 | C47: Couldn't even get past the pay wall to see if I like the app. I'm not giving you my credit card information for a trial before I even know if I want to commit to the app. Waste of time, uninstalled. | D47: Pricing & subscription | E47: paywall before trial | F47: no
A48: Monarch Money | B48: 1 | C48: trying hard to cancel after free trial. cannot be done in app, which says I have to do that in play store. no joy. I WILL NEVER BUY AN APP WHICH CHEATS ITS WAY TO FUNDS BY MAKING IT THIS DIFFICULT TO CANCEL | D48: Pricing & subscription | E48: cancellation difficulty | F48: no
A49: Monarch Money | B49: 1 | C49: No actual free version. | D49: Pricing & subscription | E49: no free version | F49: no
A50: Monarch Money | B50: 2 | C50: no push notifications | D50: Missing features | E50: push notifications | F50: no
A51: Monarch Money | B51: 2 | C51: Similar functionality and design to Mint but more connection issues and data problems. I discovered monarch when I was looking for a replacement for Mint. Mint certainly wasn't perfect, but it was free and performed well. Monarch has much of the same functionality and similar design but I have more issues with Monach connecting to accounts. This is disappointing considering there is a cost to monarch and Mint was free. | D51: Bank connection / sync | E51: compares with Mint | F51: yes
A52: Monarch Money | B52: 2 | C52: Not a good enough replacement for Mint. Creating a budget is overly complicated, I'd rather just creat custom categories than have to disable a ton that I don't need. I can't budget by pay period so I end up using a spreadsheet anyway, which defeats the purpose of the app. Its even more annoying when you have to reconcile venmo transfers with your budget categories. I regret paying for the annual version even with a coupon code. Only helpful for tracking transactions, not worth the money. | D52: Usability & design | E52: also missing pay-period budgeting | F52: yes
A53: Monarch Money | B53: 2 | C53: delay in charges showing up. not as easy as mint was. I didn't find the app easy to use. the budgeting system was okay but mint was 5x better. I just want mint back o would pay the same cost of monarch to get mint and mint was free. | D53: Usability & design | E53: also delayed transactions | F53: yes
... A58: Monarch Money | B58: 3 | C58: Would be excellent, but the reason I bought it was to track my portfolio, and they made it too difficult (too many clicks) to actually see my portfolio. Just not great attention to the dashboard. Feels more like NerdWallet, with more focus on credit score tracking than actual investments. | D58: Usability & design | E58: portfolio view too many clicks | F58: no
A59: Monarch Money | B59: 3 | C59: Still learning and think we like it so far. | D59: Praise | F59: no
A60: Monarch Money | B60: 3 | C60: App is poorly optimized for Android making it slow, glitchy, and resource hungry. The desktop browser experience is great for personal finance nuts and those transitioning over from Mint. However if your main use-case is for mobile, I do not recommend, especially as it's a paid subscription service. If you decide to give the 7 day trial a go, I recommend setting everything up in the browser and only using mobile for quick check-ins. | D60: Bugs & performance | E60: Android performance | F60: yes
A61: Monarch Money | B61: 3 | C61: Some bugs with net worth calculat.I spend too much time removing and re-adding manual accounts just because the networth looked off. Then doing so, I see the networth randomly go worse and there's no way to fix it. The account balance looks right on the accts but the numbers look wrong in the account details. Editing the account doesn't fix anything. Doing so also makes the investments charts go bad as well even tho the accounts I removed and readded had no investments. I regret paying for this. | D61: Bugs & performance | E61: net worth calculation wrong | F61: no
A62: Monarch Money | B62: 3 | C62: the monarch app is great; however, it still does not have an android widget, which is really disappointing. | D62: Missing features | E62: Android widget | F62: no
A63: Monarch Money | B63: 3 | C63: Doesn't play nice with betterment at all. It constantly misses transactions | D63: Bank connection / sync | E63: missing transactions | F63: no
A64: Monarch Money | B64: 3 | C64: So far I have barely used it but like what I see | D64: Praise | F64: no
A65: Monarch Money | B65: 3 | C65: (paid service) generally great, but Fidelity account sync shows wrong amount, significantly wrong | D65: Bank connection / sync | E65: wrong balance | F65: no
A66: Monarch Money | B66: 4 | C66: better than Mint; needs work on connections with government sites like 529 and Treasury direct and on being able to distinguish parts of payments as principle vs interest (transfers vs gains/losses) but otherwise great. invaluable tool for keeping track of accounts. | D66: Missing features | E66: also connections to government sites | F66: yes
A67: Monarch Money | B67: 4 | C67: I don't now, why I must pay that not using upp? | D67: Pricing & subscription | E67: unclear English | F67: no
A68: Monarch Money | B68: 4 | C68: Exploring the navigational simplicity! | D68: Praise | F68: no
A69: Monarch Money | B69: 4 | C69: would be 5 stars if it was free. As it's not. The current account sync issues are improved. Still not a 5 star because they insist on having you "update" your app constantly. I don't use auto-update due to secops reasons but they insist you keep updating the damn thing. Make your backend more modular to avoid this please. Otherwise GJ! | D69: Pricing & subscription | E69: also forced updates | F69: no
A70: Monarch Money | B70: 4 | C70: Not as good as Mint was, but they are dedicated and the app is accurate. Once I get used to it, I will like it maybe as much as Mint, but nostalgia has a way of paving over imperfections... RIP to the Goat. Miss you Mint. | D70: Praise | E70: mixed; Mint nostalgia | F70: yes
A71: Monarch Money | B71: 4 | C71: Almost perfect app! Some synching issues, but I do not blame it all on the app sometimes it is the banks. The one thing I wish it had is a way to project future account balance with recurring transactions. For example if I have $500 in my checking account on Monday July 1st and will get a salary check direct deposited on Friday July 5th of $200 and then will have a cell phone bill of $150 taken out on Saturday July 6th then my projected account balance for July 6th will be $550. | D71: Missing features | E71: projected balances; minor sync issues | F71: no
A72: Monarch Money | B72: 4 | C72: The app is great with tons of features. It would be even better if one could select certain transactions and see the total of the selected transactions. Sometimes, you just need to know the balance of two out of 3 accounts. One issue I've noticed is that accounts in foreign currency are not converted. If you have 10 CA in one account and 100 AED in another account, your net worth will be 110 CA, which is wrong And with a balance of -10 CA on your line of credit, the app thinks I owe the bank | D72: Missing features | E72: currency conversion | F72: no
A73: Monarch Money | B73: 4 | C73: I like all the features of the app from the reporting, to the categorization of the transactions, to seeing the net worth over time. But there are two issues: 1. The account syncing has issues. Especially with my Fidelity account, it says it syncs, but the amounts are not accurate. 2. The transactions especially from the bank accounts only go back like 3 months when you first connect it, making reports inaccurate. I recommend doing a month subscription before an annual one to test it. | D73: Bank connection / sync | E73: also short transaction history | F73: no
A74: Monarch Money | B74: 5 | C74: im still new at using it but so far so good | D74: Praise | F74: no
A75: Monarch Money | B75: 5 | C75: This is the best budgeting app for Canadians. It's very user friendly and easy to use. | D75: Praise | F75: no
A76: Monarch Money | B76: 5 | C76: I enjoy the app but do prefer the web version more, it feels more seamless | D76: Praise | E76: prefers web version | F76: no
A77: Monarch Money | B77: 5 | C77: love the new Amazon categorization functionality!!!! | D77: Praise | F77: no
A78: Monarch Money | B78: 5 | C78: love it great UI | D78: Praise | F78: no
A79: Monarch Money | B79: 5 | C79: This app is a peak budgeting tool, and they're constantly adding new features and listening to feedback | D79: Praise | F79: no
A80: Monarch Money | B80: 5 | C80: This budgeting app is awesome. I used to be a Mint user and this is way better than Mint ever was. I love being able to add multiple financial institutions and being able to share my budget with people in my household. | D80: Praise | F80: yes
A81: Monarch Money | B81: 5 | C81: Sincerely appreciate the ease of use compared to what I used to use. I was a Mint girl for years before they merged with Credit Karma. Monarch has supported me in understanding my expenses. | D81: Praise | F81: yes
A82: Rocket Money | B82: 1 | C82: Can't get my subscriptions to show up so I can cancel stuff | D82: Bank connection / sync | E82: subscriptions not detected; Rocket's core feature | F82: no
A83: Rocket Money | B83: 1 | C83: Bad Customer Service! At the start the first couple days were going good with the app. but then I was curious on getting one of my bills negotiated down. they did it the next day which was good, but then they want you to pay for their percentage for the whole first year. I would be fine to do this, but I plan on only having my internet for the next 4 months since I am selling. They tell me its final and I have to pay then anyways. A live person has not gotten back to me. Only AI bots. Not Happy | D83: Pricing & subscription | E83: bill negotiation fee; also support | F83: no
A84: Rocket Money | B84: 1 | C84: Can't even get it set up. No call, no text, can't verify. Fix your stuff | D84: Bugs & performance | E84: setup/verification; login problem | F84: no
A85: Rocket Money | B85: 1 | C85: App was great until I paid for a membership. Been trying to cancel since October of 2023. It says I cannot cancel my membership while I have an active account open. I go go the active account and try to close it and it says it cannot because it's pending a transaction from October. I've come back several times over the last 4/mo & it's never changed. I've wasted money on this app because they refuse to let me cancel my subscription. At this point I feel like I deserve a refund for scam... | D85: Pricing & subscription | E85: cancellation difficulty | F85: no
A86: Rocket Money | B86: 1 | C86: i signed up with rocket money to help me get all my subscriptions for other apps under control. i even switched to the premium account and they really didnt help me much. I decided to cancel my membership with them and found it just as difficult to cancel with them as it is with the apps they were helping me with. I finall sent a email to them and they still didnt honor my cancelation and charged me 2 additional months after i canceled my premium account and was refunded only 1 month. 😠 | D86: Pricing & subscription | E86: cancellation difficulty | F86: no
A87: Rocket Money | B87: 1 | C87: I get the verification code after it has already expired. | D87: Bugs & performance | E87: verification code; login problem | F87: no
A88: Rocket Money | B88: 1 | C88: Very unbeneficial bill negotiation. My monthly internet bill was reduced by $5, but they claim they have reduced it by $540... Huh? over how long a time? And I owe them 50 percent of that, which is 6 payments of $45... Whoa. Doesn't add up. | D88: Pricing & subscription | E88: bill negotiation fee | F88: no
A89: Rocket Money | B89: 1 | C89: I don't understand why I can't cancel rocket money I've tried twice yet they keep taking my money | D89: Pricing & subscription | E89: cancellation difficulty | F89: no
A90: Rocket Money | B90: 2 | C90: So far it cant seem to identify much very accurately. For example, it lists my car loan as a subscription and it's not terribly intuitive on finding a way to correct. | D90: Bugs & performance | E90: loan wrongly shown as subscription | F90: no
A91: Rocket Money | B91: 2 | C91: Broken. Impossible to link many accounts to the app, rendering it effectively worthless as a financial tracking app. | D91: Bank connection / sync | F91: no
A92: Rocket Money | B92: 2 | C92: So many errors | D92: Bugs & performance | E92: vague | F92: no
A93: Rocket Money | B93: 2 | C93: it was an ok app until I got a call from them trying to get me to upgrade my account... creepy after. hard pass. | D93: Privacy & trust | E93: upsell phone call | F93: no
A94: Rocket Money | B94: 2 | C94: nice idea to focus on subscription based spending together with money management, however all the app try to do is to ask you to add another subscription every second | D94: Privacy & trust | E94: upselling | F94: no
A95: Rocket Money | B95: 2 | C95: This would be a great app if it wasn't so buggy. It constantly skips picking up transactions from my bank account. I get it fixed with tech support and then the same thing happens next month. I feel like it's trying to be smart and failing utterly. | D95: Bank connection / sync | E95: missing transactions | F95: no
A96: Rocket Money | B96: 2 | C96: This app will help you "cancel" subscriptions but you have to subscribe. The ad that I hear over and over again fails to mention that tidbit. perhaps you should advertise for a "small monthly fee" you can cancel other subscriptions with just one click. Agreed, I don't doubt that it takes labor to help people manage and cancel, BUT the ads that play make a person feel as though it's free. perhaps you should add that particular disclaimer to the ads that play constantly! Just saying! | D96: Pricing & subscription | E96: ads hide the fee | F96: no
A97: Rocket Money | B97: 2 | C97: can't login anymore and no way to change phone number either got a new phone number and now I can't login. | D97: Bugs & performance | E97: login / phone number change | F97: no
A98: Rocket Money | B98: 3 | C98: For how in depth this app is it isn't very intuitive. It's can't categorize recurring payments that fluctuate, so you end up with multiple transactions, and only when you dig at transaction history can you tell. I've read the "how to's" and that hasn't fixed my problem either. It's too time consuming and doesn't show the larger picture very well. There is the calender and graph, but mostly it's individual transactions. Simplify it and make it more intuitive. Glad I chose to pay less for it. | D98: Usability & design | E98: recurring payments hard to read | F98: no
A99: Rocket Money | B99: 3 | C99: Would be a five star app if the widgets weren't iOS exclusive | D99: Missing features | E99: widgets iOS-only | F99: no
A100: Rocket Money | B100: 3 | C100: I mainly downloaded and paid for a monthly subscription with one of the reasons being Rocket Money advertised they find monthly subscriptions you may have forgot about and they cancel that subscription for you. I work many hours per week and canceling subscriptions consumes time that I just don't have. I attempted to cancel one and was given information on how to proceed with canceling it (which I already knew how to). I manage my finances by paper so A+ for saving me time with that. | D100: Pricing & subscription | E100: cancellation service didn't deliver | F100: no
A101: Rocket Money | B101: 3 | C101: Looks good! | D101: Praise | F101: no
A102: Rocket Money | B102: 3 | C102: Wasn't even capable of cancelling half of the random subscriptions automatically, I had to do them myself. The budgeting tool is good but there are better out there for free and/or significantly less than the $60 annual premium. | D102: Pricing & subscription | E102: cancellation service incomplete; value for price | F102: no
A103: Rocket Money | B103: 3 | C103: at first it was great for finding and eliminating subscriptions I no longer wanted as well as monitoring my bank accounts. Now it isn't finding subscriptions or correctly reporting my accounts. | D103: Bank connection / sync | E103: subscriptions and accounts not detected | F103: no
A104: Rocket Money | B104: 3 | C104: connecting PayPal and a bank account can make reading Rocket Money a little difficult because some of the recurring payments can be displayed twice. if PayPal is used a lot for subscriptions, and it's also connected to your bank account, Rocket Money will display a single subscription twice. one would be from PayPal and the other from the bank. very handy otherwise | D104: Bank connection / sync | E104: duplicate recurring payments | F104: no
A105: Rocket Money | B105: 3 | C105: Downgrading to 3 stars. Loses connection with my bank and resets all my data when I reconnect. Really annoying and time consuming. | D105: Bank connection / sync | E105: resets data on reconnect | F105: no
A106: Rocket Money | B106: 4 | C106: thank u so much | D106: Praise | F106: no
A107: Rocket Money | B107: 4 | C107: missing some account links and would like more budget options but overall really fantastic especially for the price. would like to be able to manually add amounts for accounts not linked | D107: Missing features | E107: account links, manual entry | F107: no
A108: Rocket Money | B108: 4 | C108: The app has a lot more capabilities than the on line version, which I find disappointing. other than that, it is very good. | D108: Missing features | E108: web version lacks features | F108: no
A109: Rocket Money | B109: 4 | C109: Still learning but feel it will keep track of my bills and spending better than myself alone. | D109: Praise | F109: no
A110: Rocket Money | B110: 4 | C110: so far so good. Just gettinng set up. | D110: Praise | F110: no
A111: Rocket Money | B111: 4 | C111: So far so good. I wish there was a way to add all of my credit cards to my expenses. I tried adding them by "adding account" section under my normal bank but it wouldn't allow it. Other than that I really like how the option is there to savor money for me and myself not even have to know how much of when. I always look at my savings account and knowing what I have makes me spend it just as I would if it was not in savings. | D111: Bank connection / sync | E111: can't add credit cards | F111: no
A112: Rocket Money | B112: 4 | C112: My only issue is I can only connect my bank accounts, and I can't do it with cashapp. The app is extremely useful and easy to navigate. If anyone is having difficulty budgeting, I highly recommend rocket money | D112: Bank connection / sync | E112: Cash App not supported | F112: no
A113: Rocket Money | B113: 4 | C113: Love this app! Unfortunately, it will not let me type in my monthly income into the text box. Maybe just a bug in the system. Would love to know if that could be fixed or if anyone else has had the same problem. | D113: Bugs & performance | E113: income field broken | F113: no
A114: Rocket Money | B114: 5 | C114: I can see every detail in my budget clear as day. I don't have to worry about wether or not I can pay a bill or utility because I know exactly what's due and how to spend. It's the most effective tool in my phone. | D114: Praise | F114: no
A115: Rocket Money | B115: 5 | C115: So far it has literally changed my life for the better, and it's only the beginning. I haven't used all of the functions yet, but just the one stop shop for a snapshot of my finances and an easy way to review my monthly spending is an amazing advantage. I highly recommend to anyone who's chaotic with their money but wants to organize their finances like me. | D115: Praise | F115: no
...

Sheet Summary
A1: Category | B1: Credit Karma | C1: Rocket Money | D1: YNAB | E1: Monarch Money | F1: Total
A2: Bank connection / sync | B2: =COUNTIFS('Labeled sample'!$D$2:$D$161,$A2,'Labeled sample'!$A$2:$A$161,B$1) -> 1 | C2: =COUNTIFS('Labeled sample'!$D$2:$D$161,$A2,'Labeled sample'!$A$2:$A$161,C$1) -> 8 | D2: =COUNTIFS('Labeled sample'!$D$2:$D$161,$A2,'Labeled sample'!$A$2:$A$161,D$1) -> 2 | E2: =COUNTIFS('Labeled sample'!$D$2:$D$161,$A2,'Labeled sample'!$A$2:$A$161,E$1) -> 6 | F2: =SUM(B2:E2) -> 17
A3: Bugs & performance | B3: =COUNTIFS('Labeled sample'!$D$2:$D$161,$A3,'Labeled sample'!$A$2:$A$161,B$1) -> 5 | C3: =COUNTIFS('Labeled sample'!$D$2:$D$161,$A3,'Labeled sample'!$A$2:$A$161,C$1) -> 6 | D3: =COUNTIFS('Labeled sample'!$D$2:$D$161,$A3,'Labeled sample'!$A$2:$A$161,D$1) -> 1 | E3: =COUNTIFS('Labeled sample'!$D$2:$D$161,$A3,'Labeled sample'!$A$2:$A$161,E$1) -> 3 | F3: =SUM(B3:E3) -> 15
A4: Pricing & subscription | B4: =COUNTIFS('Labeled sample'!$D$2:$D$161,$A4,'Labeled sample'!$A$2:$A$161,B$1) -> 0 | C4: =COUNTIFS('Labeled sample'!$D$2:$D$161,$A4,'Labeled sample'!$A$2:$A$161,C$1) -> 8 | D4: =COUNTIFS('Labeled sample'!$D$2:$D$161,$A4,'Labeled sample'!$A$2:$A$161,D$1) -> 4 | E4: =COUNTIFS('Labeled sample'!$D$2:$D$161,$A4,'Labeled sample'!$A$2:$A$161,E$1) -> 11 | F4: =SUM(B4:E4) -> 23
A5: Usability & design | B5: =COUNTIFS('Labeled sample'!$D$2:$D$161,$A5,'Labeled sample'!$A$2:$A$161,B$1) -> 2 | C5: =COUNTIFS('Labeled sample'!$D$2:$D$161,$A5,'Labeled sample'!$A$2:$A$161,C$1) -> 1 | D5: =COUNTIFS('Labeled sample'!$D$2:$D$161,$A5,'Labeled sample'!$A$2:$A$161,D$1) -> 15 | E5: =COUNTIFS('Labeled sample'!$D$2:$D$161,$A5,'Labeled sample'!$A$2:$A$161,E$1) -> 3 | F5: =SUM(B5:E5) -> 21
A6: Missing features | B6: =COUNTIFS('Labeled sample'!$D$2:$D$161,$A6,'Labeled sample'!$A$2:$A$161,B$1) -> 0 | C6: =COUNTIFS('Labeled sample'!$D$2:$D$161,$A6,'Labeled sample'!$A$2:$A$161,C$1) -> 3 | D6: =COUNTIFS('Labeled sample'!$D$2:$D$161,$A6,'Labeled sample'!$A$2:$A$161,D$1) -> 6 | E6: =COUNTIFS('Labeled sample'!$D$2:$D$161,$A6,'Labeled sample'!$A$2:$A$161,E$1) -> 5 | F6: =SUM(B6:E6) -> 14
A7: Customer support | B7: =COUNTIFS('Labeled sample'!$D$2:$D$161,$A7,'Labeled sample'!$A$2:$A$161,B$1) -> 3 | C7: =COUNTIFS('Labeled sample'!$D$2:$D$161,$A7,'Labeled sample'!$A$2:$A$161,C$1) -> 0 | D7: =COUNTIFS('Labeled sample'!$D$2:$D$161,$A7,'Labeled sample'!$A$2:$A$161,D$1) -> 0 | E7: =COUNTIFS('Labeled sample'!$D$2:$D$161,$A7,'Labeled sample'!$A$2:$A$161,E$1) -> 0 | F7: =SUM(B7:E7) -> 3
A8: Privacy & trust | B8: =COUNTIFS('Labeled sample'!$D$2:$D$161,$A8,'Labeled sample'!$A$2:$A$161,B$1) -> 7 | C8: =COUNTIFS('Labeled sample'!$D$2:$D$161,$A8,'Labeled sample'!$A$2:$A$161,C$1) -> 2 | D8: =COUNTIFS('Labeled sample'!$D$2:$D$161,$A8,'Labeled sample'!$A$2:$A$161,D$1) -> 0 | E8: =COUNTIFS('Labeled sample'!$D$2:$D$161,$A8,'Labeled sample'!$A$2:$A$161,E$1) -> 0 | F8: =SUM(B8:E8) -> 9
A9: Praise | B9: =COUNTIFS('Labeled sample'!$D$2:$D$161,$A9,'Labeled sample'!$A$2:$A$161,B$1) -> 13 | C9: =COUNTIFS('Labeled sample'!$D$2:$D$161,$A9,'Labeled sample'!$A$2:$A$161,C$1) -> 12 | D9: =COUNTIFS('Labeled sample'!$D$2:$D$161,$A9,'Labeled sample'!$A$2:$A$161,D$1) -> 10 | E9: =COUNTIFS('Labeled sample'!$D$2:$D$161,$A9,'Labeled sample'!$A$2:$A$161,E$1) -> 12 | F9: =SUM(B9:E9) -> 47
A10: Other / off-topic | B10: =COUNTIFS('Labeled sample'!$D$2:$D$161,$A10,'Labeled sample'!$A$2:$A$161,B$1) -> 9 | C10: =COUNTIFS('Labeled sample'!$D$2:$D$161,$A10,'Labeled sample'!$A$2:$A$161,C$1) -> 0 | D10: =COUNTIFS('Labeled sample'!$D$2:$D$161,$A10,'Labeled sample'!$A$2:$A$161,D$1) -> 2 | E10: =COUNTIFS('Labeled sample'!$D$2:$D$161,$A10,'Labeled sample'!$A$2:$A$161,E$1) -> 0 | F10: =SUM(B10:E10) -> 11
A11: Total | B11: =SUM(B2:B10) -> 40 | C11: =SUM(C2:C10) -> 40 | D11: =SUM(D2:D10) -> 40 | E11: =SUM(E2:E10) -> 40 | F11: =SUM(F2:F10) -> 160
A13: Labels are an AI-drafted first pass for testing categories; review before use.
